pervect
